{
  "T1_k16_kl_be1.5": [
    {
      "epoch": 1,
      "loss": 6.211144828796387,
      "perplexity": 498.27136028761174,
      "energy": 0.027736459299921988,
      "iters_per_token": 0.0,
      "seconds": 3.5219165830058046
    },
    {
      "epoch": 2,
      "loss": 5.817515981197357,
      "perplexity": 336.1360474702699,
      "energy": 0.03748055165633559,
      "iters_per_token": 0.0,
      "seconds": 3.403195457998663
    },
    {
      "epoch": 3,
      "loss": 3.820784404873848,
      "perplexity": 45.6399945177223,
      "energy": 0.6731916164979339,
      "iters_per_token": 0.0,
      "seconds": 3.344298832991626
    },
    {
      "epoch": 4,
      "loss": 1.9000880256295205,
      "perplexity": 6.686482998250083,
      "energy": 0.9295884512364865,
      "iters_per_token": 0.0,
      "seconds": 3.342917000001762
    },
    {
      "epoch": 5,
      "loss": 0.8946297064423561,
      "perplexity": 2.4464297245514346,
      "energy": 0.9835968933999538,
      "iters_per_token": 0.0,
      "seconds": 3.3538789579761215
    },
    {
      "epoch": 6,
      "loss": 0.532952350191772,
      "perplexity": 1.7039555633004577,
      "energy": 1.3776207529008389,
      "iters_per_token": 0.0,
      "seconds": 3.3336696659680456
    },
    {
      "epoch": 7,
      "loss": 0.31257647052407267,
      "perplexity": 1.3669424679840394,
      "energy": 1.903083583712578,
      "iters_per_token": 0.0,
      "seconds": 3.3488292080000974
    },
    {
      "epoch": 8,
      "loss": 0.21084228865802288,
      "perplexity": 1.2347176107337519,
      "energy": 2.7289831668138502,
      "iters_per_token": 0.0,
      "seconds": 3.3589543330017477
    },
    {
      "epoch": 9,
      "loss": 0.14374114242382346,
      "perplexity": 1.1545851967132787,
      "energy": 3.2818399727344514,
      "iters_per_token": 0.0,
      "seconds": 3.34184795798501
    },
    {
      "epoch": 10,
      "loss": 0.11144043523818255,
      "perplexity": 1.117887155340235,
      "energy": 3.808983287215233,
      "iters_per_token": 0.0,
      "seconds": 3.370817375020124
    },
    {
      "epoch": 11,
      "loss": 0.08192567965015769,
      "perplexity": 1.0853751413717152,
      "energy": 4.31145638525486,
      "iters_per_token": 0.0,
      "seconds": 3.357710833020974
    },
    {
      "epoch": 12,
      "loss": 0.06166556971147656,
      "perplexity": 1.063606582986175,
      "energy": 4.363792207837105,
      "iters_per_token": 0.0,
      "seconds": 3.380198457976803
    },
    {
      "epoch": 13,
      "loss": 0.050679493532516065,
      "perplexity": 1.051985671033868,
      "energy": 4.711028563976288,
      "iters_per_token": 0.0,
      "seconds": 3.372948207950685
    },
    {
      "epoch": 14,
      "loss": 0.03517086985521019,
      "perplexity": 1.035796680108419,
      "energy": 4.9612329185009,
      "iters_per_token": 0.0,
      "seconds": 3.356734958011657
    },
    {
      "epoch": 15,
      "loss": 0.02441818043589592,
      "perplexity": 1.0247187456360483,
      "energy": 5.2631433576345446,
      "iters_per_token": 0.0,
      "seconds": 3.3647849170374684
    },
    {
      "epoch": 16,
      "loss": 0.02065330831683241,
      "perplexity": 1.0208680638114218,
      "energy": 5.422796338796616,
      "iters_per_token": 0.0,
      "seconds": 3.354561250016559
    },
    {
      "epoch": 17,
      "loss": 0.01577149235527031,
      "perplexity": 1.0158965187603872,
      "energy": 5.535668462514877,
      "iters_per_token": 0.0,
      "seconds": 3.383433041977696
    },
    {
      "epoch": 18,
      "loss": 0.011603652255143971,
      "perplexity": 1.0116712357802475,
      "energy": 5.808426737785339,
      "iters_per_token": 0.0,
      "seconds": 3.387284665950574
    },
    {
      "epoch": 19,
      "loss": 0.009575188055168837,
      "perplexity": 1.0096211768348546,
      "energy": 6.033137321472168,
      "iters_per_token": 0.0,
      "seconds": 3.370264666969888
    },
    {
      "epoch": 20,
      "loss": 0.007911413232795894,
      "perplexity": 1.0079427911557879,
      "energy": 6.208619073033333,
      "iters_per_token": 0.0,
      "seconds": 3.3748920409707353
    },
    {
      "epoch": 21,
      "loss": 0.00683191892458126,
      "perplexity": 1.0068553097203434,
      "energy": 6.391199630498886,
      "iters_per_token": 0.0,
      "seconds": 3.3881272089784034
    },
    {
      "epoch": 22,
      "loss": 0.005960747416247613,
      "perplexity": 1.005978548021857,
      "energy": 6.563177812099457,
      "iters_per_token": 0.0,
      "seconds": 3.373740083014127
    },
    {
      "epoch": 23,
      "loss": 0.005328170454595238,
      "perplexity": 1.0053423903990033,
      "energy": 6.655705094337463,
      "iters_per_token": 0.0,
      "seconds": 3.374190083995927
    },
    {
      "epoch": 24,
      "loss": 0.0048079112137202175,
      "perplexity": 1.0048194877644132,
      "energy": 6.791632342338562,
      "iters_per_token": 0.0,
      "seconds": 3.3686480000033043
    },
    {
      "epoch": 25,
      "loss": 0.004305948849651031,
      "perplexity": 1.0043152327679752,
      "energy": 6.905968564748764,
      "iters_per_token": 0.0,
      "seconds": 3.3811684590182267
    },
    {
      "epoch": 26,
      "loss": 0.003992362317512743,
      "perplexity": 1.0040003424122257,
      "energy": 7.021420276165008,
      "iters_per_token": 0.0,
      "seconds": 3.394518041983247
    },
    {
      "epoch": 27,
      "loss": 0.003729817326529883,
      "perplexity": 1.0037367817511598,
      "energy": 7.120495694875717,
      "iters_per_token": 0.0,
      "seconds": 3.3941665409947746
    },
    {
      "epoch": 28,
      "loss": 0.0034644476385437884,
      "perplexity": 1.00347045577355,
      "energy": 7.2142906308174135,
      "iters_per_token": 0.0,
      "seconds": 3.3277780420030467
    },
    {
      "epoch": 29,
      "loss": 0.003254561455105431,
      "perplexity": 1.003259863290394,
      "energy": 7.303814268112182,
      "iters_per_token": 0.0,
      "seconds": 3.355700457992498
    },
    {
      "epoch": 30,
      "loss": 0.0030800277527305298,
      "perplexity": 1.0030847759117785,
      "energy": 7.392998999357223,
      "iters_per_token": 0.0,
      "seconds": 3.3709957089740783
    },
    {
      "epoch": 31,
      "loss": 0.002939495930331759,
      "perplexity": 1.0029438204847925,
      "energy": 7.470763450860977,
      "iters_per_token": 0.0,
      "seconds": 3.3688824999844655
    },
    {
      "epoch": 32,
      "loss": 0.0028265969071071596,
      "perplexity": 1.002830595498726,
      "energy": 7.5505362212657925,
      "iters_per_token": 0.0,
      "seconds": 3.3525257910368964
    },
    {
      "epoch": 33,
      "loss": 0.0027195908085559497,
      "perplexity": 1.0027232922503473,
      "energy": 7.625288128852844,
      "iters_per_token": 0.0,
      "seconds": 3.381713167007547
    },
    {
      "epoch": 34,
      "loss": 0.0026255014308844693,
      "perplexity": 1.0026289510781234,
      "energy": 7.690857517719269,
      "iters_per_token": 0.0,
      "seconds": 3.3629576669773087
    },
    {
      "epoch": 35,
      "loss": 0.0025539227004628628,
      "perplexity": 1.0025571867391523,
      "energy": 7.757081681489945,
      "iters_per_token": 0.0,
      "seconds": 3.3636927920160815
    },
    {
      "epoch": 36,
      "loss": 0.002487455761001911,
      "perplexity": 1.0024905520458416,
      "energy": 7.8247442781925205,
      "iters_per_token": 0.0,
      "seconds": 3.3730631670332514
    },
    {
      "epoch": 37,
      "loss": 0.002428745223733131,
      "perplexity": 1.0024316970146463,
      "energy": 7.893615472316742,
      "iters_per_token": 0.0,
      "seconds": 3.4174207919859327
    },
    {
      "epoch": 38,
      "loss": 0.0023740369113511408,
      "perplexity": 1.0023768571683358,
      "energy": 7.950840455293656,
      "iters_per_token": 0.0,
      "seconds": 3.3879264579736628
    },
    {
      "epoch": 39,
      "loss": 0.0023292452897294424,
      "perplexity": 1.002331960088941,
      "energy": 8.0126957654953,
      "iters_per_token": 0.0,
      "seconds": 3.389335250016302
    },
    {
      "epoch": 40,
      "loss": 0.0022905397010617888,
      "perplexity": 1.002293164991184,
      "energy": 8.06574975848198,
      "iters_per_token": 0.0,
      "seconds": 3.3671137499623
    },
    {
      "epoch": 41,
      "loss": 0.002257353928871453,
      "perplexity": 1.002259903670447,
      "energy": 8.125743740797043,
      "iters_per_token": 0.0,
      "seconds": 3.36197958298726
    },
    {
      "epoch": 42,
      "loss": 0.0022259846693486905,
      "perplexity": 1.0022284640125414,
      "energy": 8.176470667123795,
      "iters_per_token": 0.0,
      "seconds": 3.400830833998043
    },
    {
      "epoch": 43,
      "loss": 0.0021995956427417695,
      "perplexity": 1.0022020165279015,
      "energy": 8.22611179947853,
      "iters_per_token": 0.0,
      "seconds": 3.3663367909612134
    },
    {
      "epoch": 44,
      "loss": 0.0021765587473055346,
      "perplexity": 1.0021789291707723,
      "energy": 8.277911353111268,
      "iters_per_token": 0.0,
      "seconds": 3.387805125035811
    },
    {
      "epoch": 45,
      "loss": 0.0021733674991992304,
      "perplexity": 1.0021757309742656,
      "energy": 8.416406643390655,
      "iters_per_token": 0.0,
      "seconds": 3.3929830830311403
    },
    {
      "epoch": 46,
      "loss": 0.002162366967240814,
      "perplexity": 1.0021647065687465,
      "energy": 8.487005478143692,
      "iters_per_token": 0.0,
      "seconds": 3.400317542022094
    },
    {
      "epoch": 47,
      "loss": 0.0021359350081183947,
      "perplexity": 1.0021382177422657,
      "energy": 8.516777867078781,
      "iters_per_token": 0.0,
      "seconds": 3.386901999998372
    },
    {
      "epoch": 48,
      "loss": 0.002121633516799193,
      "perplexity": 1.0021238857737287,
      "energy": 8.560821026563644,
      "iters_per_token": 0.0,
      "seconds": 3.3738813750096597
    },
    {
      "epoch": 49,
      "loss": 0.002108963075443171,
      "perplexity": 1.0021111885022427,
      "energy": 8.600713670253754,
      "iters_per_token": 0.0,
      "seconds": 3.3937685420387425
    }
  ],
  "T2_k16_kl_be1.5": [
    {
      "epoch": 1,
      "loss": 6.16822270154953,
      "perplexity": 477.33698146133185,
      "energy": 0.029505411093123258,
      "iters_per_token": 0.0,
      "seconds": 4.537423417030368
    },
    {
      "epoch": 2,
      "loss": 4.1822683095932005,
      "perplexity": 65.51429149426481,
      "energy": 21.041231113672257,
      "iters_per_token": 0.0,
      "seconds": 4.572388915985357
    },
    {
      "epoch": 3,
      "loss": 1.2627866297960282,
      "perplexity": 3.5352592326365913,
      "energy": 28.641707324981688,
      "iters_per_token": 0.0,
      "seconds": 4.579415666987188
    },
    {
      "epoch": 4,
      "loss": 0.5825885700061917,
      "perplexity": 1.7906677052774687,
      "energy": 45.86060609817505,
      "iters_per_token": 0.0,
      "seconds": 4.570786833006423
    },
    {
      "epoch": 5,
      "loss": 0.20784777770750223,
      "perplexity": 1.2310257657215276,
      "energy": 74.2140851020813,
      "iters_per_token": 0.0,
      "seconds": 4.563895625004079
    },
    {
      "epoch": 6,
      "loss": 0.11765124201774597,
      "perplexity": 1.124851741926483,
      "energy": 110.33076763153076,
      "iters_per_token": 0.0,
      "seconds": 4.517422625038307
    },
    {
      "epoch": 7,
      "loss": 0.061259382660500704,
      "perplexity": 1.063174647494074,
      "energy": 142.47633056640626,
      "iters_per_token": 0.0,
      "seconds": 4.618151457980275
    },
    {
      "epoch": 8,
      "loss": 0.04630303559824824,
      "perplexity": 1.0473917598590505,
      "energy": 169.50258979797363,
      "iters_per_token": 0.0,
      "seconds": 4.629491250030696
    },
    {
      "epoch": 9,
      "loss": 0.04384410558268428,
      "perplexity": 1.0448194606706027,
      "energy": 188.08629398345948,
      "iters_per_token": 0.0,
      "seconds": 4.615049000014551
    },
    {
      "epoch": 10,
      "loss": 0.04427723661065101,
      "perplexity": 1.0452721024171587,
      "energy": 202.58185386657715,
      "iters_per_token": 0.0,
      "seconds": 4.611615457979497
    },
    {
      "epoch": 11,
      "loss": 0.04567383755929768,
      "perplexity": 1.0467329503003102,
      "energy": 215.74148502349854,
      "iters_per_token": 0.0,
      "seconds": 4.612237291992642
    },
    {
      "epoch": 12,
      "loss": 0.046975835179910067,
      "perplexity": 1.048096681705891,
      "energy": 225.54708557128907,
      "iters_per_token": 0.0,
      "seconds": 4.583512958022766
    },
    {
      "epoch": 13,
      "loss": 0.048162132129073144,
      "perplexity": 1.0493407733870086,
      "energy": 233.6185998916626,
      "iters_per_token": 0.0,
      "seconds": 4.5913068749941885
    },
    {
      "epoch": 14,
      "loss": 0.04925972386263311,
      "perplexity": 1.0504931534512916,
      "energy": 240.59029445648193,
      "iters_per_token": 0.0,
      "seconds": 4.62690316705266
    },
    {
      "epoch": 15,
      "loss": 0.0502601558342576,
      "perplexity": 1.051544626263788,
      "energy": 246.72993545532228,
      "iters_per_token": 0.0,
      "seconds": 4.6062500000116415
    },
    {
      "epoch": 16,
      "loss": 0.051104275463148954,
      "perplexity": 1.0524326304616314,
      "energy": 251.7566711425781,
      "iters_per_token": 0.0,
      "seconds": 4.637423459033016
    },
    {
      "epoch": 17,
      "loss": 0.05201203916221857,
      "perplexity": 1.053388424351145,
      "energy": 256.9755264282227,
      "iters_per_token": 0.0,
      "seconds": 4.619416208006442
    },
    {
      "epoch": 18,
      "loss": 0.052776577230542895,
      "perplexity": 1.054194087843255,
      "energy": 261.30287780761716,
      "iters_per_token": 0.0,
      "seconds": 4.643109457974788
    },
    {
      "epoch": 19,
      "loss": 0.053445507772266865,
      "perplexity": 1.0548995063772149,
      "energy": 265.0089958190918,
      "iters_per_token": 0.0,
      "seconds": 4.644269750046078
    },
    {
      "epoch": 20,
      "loss": 0.054219516925513744,
      "perplexity": 1.0557163243224106,
      "energy": 269.15544776916505,
      "iters_per_token": 0.0,
      "seconds": 4.638643917045556
    },
    {
      "epoch": 21,
      "loss": 0.05485028084367514,
      "perplexity": 1.0563824421470664,
      "energy": 272.53283004760743,
      "iters_per_token": 0.0,
      "seconds": 4.612383667030372
    },
    {
      "epoch": 22,
      "loss": 0.05538795124739408,
      "perplexity": 1.0569505804431039,
      "energy": 275.41208724975587,
      "iters_per_token": 0.0,
      "seconds": 4.626813457987737
    },
    {
      "epoch": 23,
      "loss": 0.0559475552290678,
      "perplexity": 1.0575422197227606,
      "energy": 278.36461639404297,
      "iters_per_token": 0.0,
      "seconds": 4.661163083044812
    },
    {
      "epoch": 24,
      "loss": 0.05657884203828871,
      "perplexity": 1.0582100429480839,
      "energy": 281.6604694366455,
      "iters_per_token": 0.0,
      "seconds": 4.650371290976182
    },
    {
      "epoch": 25,
      "loss": 0.057103997096419334,
      "perplexity": 1.0587659132509781,
      "energy": 284.403396987915,
      "iters_per_token": 0.0,
      "seconds": 4.6461130829993635
    },
    {
      "epoch": 26,
      "loss": 0.057570444466546175,
      "perplexity": 1.0592598870242214,
      "energy": 286.837699508667,
      "iters_per_token": 0.0,
      "seconds": 4.561049875046592
    },
    {
      "epoch": 27,
      "loss": 0.05818642801605165,
      "perplexity": 1.0599125746910745,
      "energy": 290.01599235534667,
      "iters_per_token": 0.0,
      "seconds": 4.603532875014935
    },
    {
      "epoch": 28,
      "loss": 0.058694386994466184,
      "perplexity": 1.0604511035634319,
      "energy": 292.6300533294678,
      "iters_per_token": 0.0,
      "seconds": 4.61828495899681
    },
    {
      "epoch": 29,
      "loss": 0.0590918954461813,
      "perplexity": 1.0608727256333452,
      "energy": 294.6854755401611,
      "iters_per_token": 0.0,
      "seconds": 4.611452082986943
    },
    {
      "epoch": 30,
      "loss": 0.05940065640024841,
      "perplexity": 1.0612003322817236,
      "energy": 296.2864112854004,
      "iters_per_token": 0.0,
      "seconds": 4.637616958993021
    },
    {
      "epoch": 31,
      "loss": 0.05987681625410914,
      "perplexity": 1.0617057535979804,
      "energy": 298.72963790893556,
      "iters_per_token": 0.0,
      "seconds": 4.644258833024651
    },
    {
      "epoch": 32,
      "loss": 0.06021550609730184,
      "perplexity": 1.062065403454622,
      "energy": 300.46838569641113,
      "iters_per_token": 0.0,
      "seconds": 4.597614000027534
    },
    {
      "epoch": 33,
      "loss": 0.06056318571791053,
      "perplexity": 1.0624347261504237,
      "energy": 302.2498439788818,
      "iters_per_token": 0.0,
      "seconds": 4.613384625001345
    },
    {
      "epoch": 34,
      "loss": 0.06088649262674153,
      "perplexity": 1.0627782741703018,
      "energy": 303.9049602508545,
      "iters_per_token": 0.0,
      "seconds": 4.604809791024309
    },
    {
      "epoch": 35,
      "loss": 0.061083039920777085,
      "perplexity": 1.062987180893603,
      "energy": 304.91967849731446,
      "iters_per_token": 0.0,
      "seconds": 4.594752375036478
    },
    {
      "epoch": 36,
      "loss": 0.061322437645867464,
      "perplexity": 1.063241688069513,
      "energy": 306.1477394104004,
      "iters_per_token": 0.0,
      "seconds": 4.6088110829587094
    },
    {
      "epoch": 37,
      "loss": 0.061621909076347944,
      "perplexity": 1.0635601462609707,
      "energy": 307.67285385131834,
      "iters_per_token": 0.0,
      "seconds": 4.639240832999349
    },
    {
      "epoch": 38,
      "loss": 0.062000553496181963,
      "perplexity": 1.0639629336272922,
      "energy": 309.5846565246582,
      "iters_per_token": 0.0,
      "seconds": 4.639793917012867
    },
    {
      "epoch": 39,
      "loss": 0.06225803522393107,
      "perplexity": 1.064236919913421,
      "energy": 310.89380683898924,
      "iters_per_token": 0.0,
      "seconds": 4.581944334029686
    },
    {
      "epoch": 40,
      "loss": 0.06236822651699185,
      "perplexity": 1.0643541960170333,
      "energy": 311.4537464141846,
      "iters_per_token": 0.0,
      "seconds": 4.62417720904341
    },
    {
      "epoch": 41,
      "loss": 0.06265834895893932,
      "perplexity": 1.0646630338537062,
      "energy": 312.92204132080076,
      "iters_per_token": 0.0,
      "seconds": 4.604107041028328
    },
    {
      "epoch": 42,
      "loss": 0.06286093275994062,
      "perplexity": 1.0648787391863552,
      "energy": 313.9548656463623,
      "iters_per_token": 0.0,
      "seconds": 4.646491250023246
    },
    {
      "epoch": 43,
      "loss": 0.06311629181727767,
      "perplexity": 1.0651507003397662,
      "energy": 315.2550556182861,
      "iters_per_token": 0.0,
      "seconds": 4.611371207982302
    },
    {
      "epoch": 44,
      "loss": 0.06344772921875119,
      "perplexity": 1.0655037896303308,
      "energy": 316.92694091796875,
      "iters_per_token": 0.0,
      "seconds": 4.666618792049121
    },
    {
      "epoch": 45,
      "loss": 0.06373515827581286,
      "perplexity": 1.0658100903976415,
      "energy": 318.38025321960447,
      "iters_per_token": 0.0,
      "seconds": 4.587869083043188
    },
    {
      "epoch": 46,
      "loss": 0.06399896023795008,
      "perplexity": 1.0660912902796635,
      "energy": 319.6964389801025,
      "iters_per_token": 0.0,
      "seconds": 4.671212374989409
    },
    {
      "epoch": 47,
      "loss": 0.06423752941191196,
      "perplexity": 1.0663456571389929,
      "energy": 320.89745750427244,
      "iters_per_token": 0.0,
      "seconds": 4.663802333001513
    },
    {
      "epoch": 48,
      "loss": 0.0644967787899077,
      "perplexity": 1.0666221424251052,
      "energy": 322.21094818115233,
      "iters_per_token": 0.0,
      "seconds": 4.657615582982544
    },
    {
      "epoch": 49,
      "loss": 0.06470409389585256,
      "perplexity": 1.0668432922306208,
      "energy": 323.26333541870116,
      "iters_per_token": 0.0,
      "seconds": 4.672314208000898
    }
  ]
}